{
    "text": "Department Library-CSE \u2013 Siddhartha University Skip to content Search Search Home Faculty Faculty Staff Research Projects & Grants In-house Projects Faculty Publications Faculty Participations IPRs Consultancy Research Group Students Internships Publications Achievements Professional Societies Innovative Models Placements Infrastructure Academic Labs Specialized Labs AR/VR/XR Laboratory Cyber Security Lab Central Server Room Innovation Hub Department Library Events Updates News Letters Home Faculty Faculty Staff Research Projects & Grants In-house Projects Faculty Publications Faculty Participations IPRs Consultancy Research Group Students Internships Publications Achievements Professional Societies Innovative Models Placements Infrastructure Academic Labs Specialized Labs AR/VR/XR Laboratory Cyber Security Lab Central Server Room Innovation Hub Department Library Events Updates News Letters Department Library The Department Library of the Computer Science and Engineering (CSE) department offers a comprehensive array of software and digital resources to support academic and research needs. The library contains a good number of Books, E-Books, Journals, and e-resources, including Knimbus and DELNET. These resources are readily accessible both on-site and remotely for all registered users within the campus network. Students and faculty can utilize their designated login credentials to seamlessly explore and utilize the available resources, fostering a conducive environment for learning and research within the department. Library Resources Total Number of Books 603 Total Number of E-Books 1038 Total Number of Journals/Magazines National 17 International (Online Only) IEEE, ASCE, ELSEVIER, J-GATE, N-List, Delnet 686 Total Number of Project Reports 420 Total Number of CD-ROM 100 Library Software Libsys LSM 10 Online Public Access Catalogue (OPAC) \u2013 For checking Library Books (Title/Author/Keywords) of the total collection available in the Library. Total Number of Computers 11 view >> List of Department Books view >> List of Journals view >> List of e-books Contact Us registrar@siddhartha.edu.in +0866 2582333 Explore Vision and Mission Institutional Development Plan Governing Body (VRSEC) Academic Council (VRSEC) Academic Audit Reports Academic Details Academic Programs Ph.D. Programmes Curriculum and Syllabus Academic Calendar NIRF Reports For Placement-related Queries/Contact: Mr.K.Srinivas Head \u2013 Industry Relations Training & Placements tpo@siddhartha.edu.in placements@vrsiddhartha.ac.in Ph: 9440219816 8919854050 Social Links Quick Info AICTE Mandatory Disclosure AICTE Scholarship/Fellowship Schemes Press Coverage Committees Curriculum and Syllabus Academic Calendar Online payments AICTE Feedback Anti-Ragging Helpline Quick Links Public-Self-Disclosure NBA-DCS SAHE LMS Online Grievance IIC Scale of Punishment for Malpractice Policies Library Academic Bank of Credits(ABC) @2026 SIDDHARTHA ACADEMY OF HIGHER EDUCATION All rights reserved. Last Updated: May 2, 2026 Scroll to Top Contact Us Overview Overview Overview Overview Overview Vision and Mission Institutional Development Plan Constituent Units Explore Overview Overview Overview Overview Overview Vision and Mission Institutional Development Plan Constituent Units Overview Overview Overview Overview Overview Overview Overview Overview Overview All B Tech Semester end supplementary examinations scheduled on 21-03-2026 FN & AN are postponed due to Holiday declared by Govt. of Andhra Pradesh on the eve of Ramzan. The Exact Date & Time will be Announced 1st & 2nd year - B.Sc & B.Com students Tutition Fee 2023-24 Academic Year: Pending Tuition Fee Reimbursement Amount Released to ST Category Students by Govt. of A.P 1st & 2nd year M.Tech Students Tuition Fee. 1st & 2nd year M.Tech Students Tuition Fee. Instructions on Pending Fee Clearance and IV Semester Schedule \u2013 II B.Tech. Notice: Tuition fee payment for B.Tech II & IV semester students Instructions on Pending Fee Clearance and II Semester Schedule \u2013 I B.Tech. MBA tuition fee circular MCA 1st & 2nd year Fee circular 2nd year B.Sc & B.Com Tuition Fee Circular 2nd year M.Tech Fee Circular Admissions open 2026-27",
    "metadata": {
        "domain": "university",
        "source_type": "web",
        "source_name": "siddhartha.edu.in_infrastructure_csedept-library_.txt"
    }
}